cmods/__about__.py
cmods/__init__.py
cmods/cli.py
cmods/api/__init__.py
cmods/api/download.py
cmods/api/init.py
cmods/api/make.py
cmods/api/manage.py
cmods-1.0.7.dist-info/METADATA
cmods-1.0.7.dist-info/WHEEL
cmods-1.0.7.dist-info/entry_points.txt
cmods-1.0.7.dist-info/licenses/LICENSE.txt
cmods-1.0.7.dist-info/RECORD
